syslibrary/__init__.py
syslibrary/model.py
syslibrary/syslib.py
syslibrary/syslib_mflike.py
syslibrary/data/cl_generic_template_145_145.dat
syslibrary/data/cl_generic_template_145_225.dat
syslibrary/data/cl_generic_template_145_93.dat
syslibrary/data/cl_generic_template_225_145.dat
syslibrary/data/cl_generic_template_225_225.dat
syslibrary/data/cl_generic_template_225_93.dat
syslibrary/data/cl_generic_template_93_145.dat
syslibrary/data/cl_generic_template_93_225.dat
syslibrary/data/cl_generic_template_93_93.dat
syslibrary/data/test_template.yaml
syslibrary-0.2.dist-info/METADATA
syslibrary-0.2.dist-info/WHEEL
syslibrary-0.2.dist-info/top_level.txt
syslibrary-0.2.dist-info/RECORD
