Metadata-Version: 2.1
Name: syslibrary
Version: 0.2
Summary: Systematics library
Author: Simons Observatory sys crew
Author-email: 
Requires-Python: >3
